azure/mgmt/postgresqlflexibleservers/__init__.py
azure/mgmt/postgresqlflexibleservers/_configuration.py
azure/mgmt/postgresqlflexibleservers/_patch.py
azure/mgmt/postgresqlflexibleservers/_postgre_sql_management_client.py
azure/mgmt/postgresqlflexibleservers/_serialization.py
azure/mgmt/postgresqlflexibleservers/_vendor.py
azure/mgmt/postgresqlflexibleservers/_version.py
azure/mgmt/postgresqlflexibleservers/py.typed
azure/mgmt/postgresqlflexibleservers/aio/__init__.py
azure/mgmt/postgresqlflexibleservers/aio/_configuration.py
azure/mgmt/postgresqlflexibleservers/aio/_patch.py
azure/mgmt/postgresqlflexibleservers/aio/_postgre_sql_management_client.py
azure/mgmt/postgresqlflexibleservers/aio/_vendor.py
azure/mgmt/postgresqlflexibleservers/aio/operations/__init__.py
azure/mgmt/postgresqlflexibleservers/aio/operations/_administrators_operations.py
azure/mgmt/postgresqlflexibleservers/aio/operations/_backups_operations.py
azure/mgmt/postgresqlflexibleservers/aio/operations/_check_name_availability_operations.py
azure/mgmt/postgresqlflexibleservers/aio/operations/_check_name_availability_with_location_operations.py
azure/mgmt/postgresqlflexibleservers/aio/operations/_configurations_operations.py
azure/mgmt/postgresqlflexibleservers/aio/operations/_databases_operations.py
azure/mgmt/postgresqlflexibleservers/aio/operations/_firewall_rules_operations.py
azure/mgmt/postgresqlflexibleservers/aio/operations/_flexible_server_operations.py
azure/mgmt/postgresqlflexibleservers/aio/operations/_get_private_dns_zone_suffix_operations.py
azure/mgmt/postgresqlflexibleservers/aio/operations/_location_based_capabilities_operations.py
azure/mgmt/postgresqlflexibleservers/aio/operations/_log_files_operations.py
azure/mgmt/postgresqlflexibleservers/aio/operations/_ltr_backup_operations_operations.py
azure/mgmt/postgresqlflexibleservers/aio/operations/_migrations_operations.py
azure/mgmt/postgresqlflexibleservers/aio/operations/_operations.py
azure_mgmt_postgresqlflexibleservers-1.0.0.dist-info/LICENSE
azure_mgmt_postgresqlflexibleservers-1.0.0.dist-info/METADATA
azure_mgmt_postgresqlflexibleservers-1.0.0.dist-info/WHEEL
azure_mgmt_postgresqlflexibleservers-1.0.0.dist-info/top_level.txt
azure_mgmt_postgresqlflexibleservers-1.0.0.dist-info/RECORD
